myrtio_udp/__init__.py
myrtio_udp/persistent_stream.py
myrtio_udp/udp_transport.py
myrtio_udp-1.0.1.dist-info/METADATA
myrtio_udp-1.0.1.dist-info/WHEEL
myrtio_udp-1.0.1.dist-info/top_level.txt
myrtio_udp-1.0.1.dist-info/RECORD
